mwcomposerfromhell/__init__.py
mwcomposerfromhell/__main__.py
mwcomposerfromhell/composer.py
mwcomposerfromhell/magic_words.py
mwcomposerfromhell/namespace.py
mwcomposerfromhell/nodes.py
mwcomposerfromhell/parser_tests_parser.py
mwcomposerfromhell-0.5.dist-info/LICENSE
mwcomposerfromhell-0.5.dist-info/METADATA
mwcomposerfromhell-0.5.dist-info/WHEEL
mwcomposerfromhell-0.5.dist-info/top_level.txt
mwcomposerfromhell-0.5.dist-info/RECORD
