Metadata-Version: 2.1
Name: mwcomposerfromhell
Version: 0.5
Summary: Convert the parsed MediaWiki wikicode (using mwparserfromhell) to HTML.
Home-page: https://github.com/clokep/mwcomposerfromhell
Author: Patrick Cloke
Author-email: clokep@patrick.cloke.us
Classifier: Development Status :: 3 - Alpha
Classifier: Intended Audience :: Developers
Classifier: Topic :: Software Development :: Libraries :: Python Modules
Classifier: Topic :: Internet
Classifier: Programming Language :: Python
Classifier: Programming Language :: Python :: 3.7
Classifier: Programming Language :: Python :: 3.8
Classifier: Programming Language :: Python :: 3.9
Classifier: Programming Language :: Python :: 3.10
Classifier: Programming Language :: Python :: 3.11
Classifier: License :: OSI Approved :: ISC License (ISCL)
Requires-Python: >=3.7
License-File: LICENSE
Requires-Dist: mwparserfromhell (>=0.6.2)
Provides-Extra: dev
Requires-Dist: pytest (==6.2.4) ; extra == 'dev'
Requires-Dist: coverage ; extra == 'dev'
Requires-Dist: flake8 (==3.9.2) ; extra == 'dev'
Requires-Dist: flake8-builtins (==1.5.3) ; extra == 'dev'
Requires-Dist: flake8-import-order (==0.18.1) ; extra == 'dev'
Requires-Dist: importlib-metadata (<5) ; extra == 'dev'
Requires-Dist: mypy ; extra == 'dev'
Requires-Dist: black ; extra == 'dev'
